{
  "symbol": "NVDA",
  "lookback": 28,
  "horizon": 28,
  "test_start": "2025-05-28",
  "n_valid_windows": 155,
  "parse_failures": 0,
  "date_range": [
    "2025-05-28",
    "2026-01-07"
  ],
  "metrics_per_step": [
    {
      "horizon_step": 1,
      "mae": 4.293077419354839,
      "rmse": 5.873875653565403,
      "mape": 2.4237299273696213,
      "n_samples": 155
    },
    {
      "horizon_step": 7,
      "mae": 8.084154838709678,
      "rmse": 10.031286486176233,
      "mape": 4.5540865317579176,
      "n_samples": 155
    },
    {
      "horizon_step": 14,
      "mae": 9.875832258064516,
      "rmse": 12.575566405765047,
      "mape": 5.595886270106601,
      "n_samples": 155
    },
    {
      "horizon_step": 21,
      "mae": 12.511154838709675,
      "rmse": 16.871261722134896,
      "mape": 7.034421318572735,
      "n_samples": 155
    },
    {
      "horizon_step": 28,
      "mae": 14.17014193548387,
      "rmse": 20.178585130233103,
      "mape": 7.872622431600294,
      "n_samples": 155
    }
  ]
}