{
  "symbol": "WFC",
  "lookback": 7,
  "horizon": 28,
  "test_start": "2025-05-28",
  "n_valid_windows": 154,
  "parse_failures": 1,
  "date_range": [
    "2025-05-28",
    "2026-01-07"
  ],
  "metrics_per_step": [
    {
      "horizon_step": 1,
      "mae": 1.4716753246753251,
      "rmse": 2.211226377128559,
      "mape": 1.8162862758408764,
      "n_samples": 154
    },
    {
      "horizon_step": 7,
      "mae": 2.888318181818182,
      "rmse": 3.8041072890014243,
      "mape": 3.567436633085049,
      "n_samples": 154
    },
    {
      "horizon_step": 14,
      "mae": 4.707818181818182,
      "rmse": 5.855726396986427,
      "mape": 5.710240225604514,
      "n_samples": 154
    },
    {
      "horizon_step": 21,
      "mae": 6.422207792207792,
      "rmse": 8.011449911739552,
      "mape": 7.714983311257597,
      "n_samples": 154
    },
    {
      "horizon_step": 28,
      "mae": 8.610662337662339,
      "rmse": 10.693004694780482,
      "mape": 10.32644984747747,
      "n_samples": 154
    }
  ]
}